pyhanja-0.0.6.dist-info/WHEEL
pyhanja-0.0.6.dist-info/top_level.txt
pyhanja-0.0.6.dist-info/RECORD
pyhanja-0.0.6.dist-info/METADATA
pyhanja-0.0.6.dist-info/LICENSE
pyhanja/__init__.py
pyhanja/_pyhanja.pypy39-pp73-aarch64-linux-gnu.so
pyhanja/data/__init__.py
pyhanja/data/hanja.txt
pyhanja/data/ks_normalize.txt
